strelix/__init__.py
strelix/__main__.py
strelix/__version__.py
strelix/cli.py
strelix-0.1.3.dist-info/licenses/LICENSE
strelix-0.1.3.dist-info/METADATA
strelix-0.1.3.dist-info/WHEEL
strelix-0.1.3.dist-info/entry_points.txt
strelix-0.1.3.dist-info/top_level.txt
strelix-0.1.3.dist-info/RECORD
