Metadata-Version: 2.4
Name: strelix
Version: 0.1.3
Summary: Strelix CLI for webhook forwarding
License: MIT
Project-URL: Homepage, https://github.com/Strelix/cli
Requires-Python: >=3.8
License-File: LICENSE
Requires-Dist: click
Requires-Dist: requests
Dynamic: license-file
